ebooklib/__init__.py
ebooklib/epub.py
ebooklib/utils.py
ebooklib/plugins/__init__.py
ebooklib/plugins/base.py
ebooklib/plugins/booktype.py
ebooklib/plugins/sourcecode.py
ebooklib/plugins/standard.py
ebooklib/plugins/tidyhtml.py
EbookLib.changyy-0.18.2023.1221.0.dist-info/AUTHORS.txt
EbookLib.changyy-0.18.2023.1221.0.dist-info/LICENSE.txt
EbookLib.changyy-0.18.2023.1221.0.dist-info/METADATA
EbookLib.changyy-0.18.2023.1221.0.dist-info/WHEEL
EbookLib.changyy-0.18.2023.1221.0.dist-info/top_level.txt
EbookLib.changyy-0.18.2023.1221.0.dist-info/RECORD
